custom_test_descriptor.py
setup.py
nose_customdescription.egg-info/PKG-INFO
nose_customdescription.egg-info/SOURCES.txt
nose_customdescription.egg-info/dependency_links.txt
nose_customdescription.egg-info/entry_points.txt
nose_customdescription.egg-info/top_level.txt