Metadata-Version: 1.0
Name: nose-customdescription
Version: 0.1.5
Summary: A Nose plugin to override test description output when using the verbose flag (-v)
Home-page: https://github.com/tamers/nosetests-description
Author: Tamer Sherif
Author-email: me@tamer.sh
License: UNKNOWN
Keywords: nose test custom description python
Platform: UNKNOWN
